{
  "players": [
    {
      "Player Name": "Michael Jordan",
      "Total GOAT Points": 9000000,
      "image": "https://clutchpoints.com/_next/image?url=https%3A%2F%2Fclutchpoints-profile-pics.s3.amazonaws.com%2Fheadshots%2Fjordanm.png&w=320&q=100",
      "Tier": "Tier 1",
      "Achievements": {
        "6x NBA Champion": true,
        "6x Finals MVP": true,
        "5x MVP": true,
        "14x All-Star": true,
        "10x All-NBA First Team": true,
        "9x All-Defensive First Team": true,
        "Defensive Player of the Year": true,
        "Rookie of the Year": true
      },
      "rank": 1
    },
    {
      "Player Name": "LeBron James",
      "Total GOAT Points": 7700000,
      "image": "https://www.thesportsdb.com/images/media/player/cutout/tx6wea1702374040.png",
      "Tier": "Tier 1",
      "Achievements": {
        "4x NBA Champion": true,
        "4x Finals MVP": true,
        "4x MVP": true,
        "19x All-Star": true,
        "13x All-NBA First Team": true,
        "5x All-Defensive First Team": true,
        "Rookie of the Year": true
      },
      "rank": 2
    },
    {
      "Player Name": "Kobe Bryant",
      "Total GOAT Points": 6500000,
      "image": "https://www.thesportsdb.com/images/media/player/cutout/8em6v71713719158.png",
      "Tier": "Tier 1",
      "Achievements": {
        "5x NBA Champion": true,
        "2x Finals MVP": true,
        "1x MVP": true,
        "18x All-Star": true,
        "11x All-NBA First Team": true,
        "9x All-Defensive First Team": true
      },
      "rank": 3
    },
    {
      "Player Name": "Kareem Abdul-Jabbar",
      "Total GOAT Points": 6300000,
      "image": "https://www.thesportsdb.com/images/media/player/cutout/o9rfqm1522695254.png",
      "Tier": "Tier 1",
      "Achievements": {
        "6x NBA Champion": true,
        "2x Finals MVP": true,
        "6x MVP": true,
        "19x All-Star": true,
        "10x All-NBA First Team": true,
        "5x All-Defensive First Team": true,
        "Rookie of the Year": true
      },
      "rank": 4
    },
    {
      "Player Name": "Bill Russell",
      "Total GOAT Points": 6100000,
      "image": "https://www.thesportsdb.com/images/media/player/cutout/ifh7ty1586513020.png",
      "Tier": "Tier 1",
      "Achievements": {
        "11x NBA Champion": true,
        "5x MVP": true,
        "12x All-Star": true,
        "3x All-NBA First Team": true,
        "1x All-Defensive First Team": true
      },
      "rank": 5
    },
    {
      "Player Name": "Shaquille O'Neal",
      "Total GOAT Points": 5900000,
      "image": "https://cdn.nba.com/headshots/nba/latest/1040x760/406.png",
      "Tier": "Tier 1",
      "Achievements": {
        "4x NBA Champion": true,
        "3x Finals MVP": true,
        "1x MVP": true,
        "15x All-Star": true,
        "8x All-NBA First Team": true
      },
      "rank": 6
    },
    {
      "Player Name": "Magic Johnson",
      "Total GOAT Points": 5700000,
      "image": "https://www.thesportsdb.com/images/media/player/cutout/5n6ypp1522695533.png",
      "Tier": "Tier 1",
      "Achievements": {
        "5x NBA Champion": true,
        "3x Finals MVP": true,
        "3x MVP": true,
        "12x All-Star": true,
        "9x All-NBA First Team": true,
        "Rookie of the Year": true
      },
      "rank": 7
    },
    {
      "Player Name": "Wilt Chamberlain",
      "Total GOAT Points": 5500000,
      "image": "https://www.thesportsdb.com/images/media/player/cutout/jp7weo1586512253.png",
      "Tier": "Tier 1",
      "Achievements": {
        "2x NBA Champion": true,
        "1x Finals MVP": true,
        "4x MVP": true,
        "13x All-Star": true,
        "7x All-NBA First Team": true,
        "2x All-Defensive First Team": true,
        "Rookie of the Year": true
      },
      "rank": 8
    },
    {
      "Player Name": "Larry Bird",
      "Total GOAT Points": 5300000,
      "image": "https://www.thesportsdb.com/images/media/player/cutout/n7qw141493061483.png",
      "Tier": "Tier 1",
      "Achievements": {
        "3x NBA Champion": true,
        "2x Finals MVP": true,
        "3x MVP": true,
        "12x All-Star": true,
        "9x All-NBA First Team": true,
        "Rookie of the Year": true
      },
      "rank": 9
    },
    {
      "Player Name": "Tim Duncan",
      "Total GOAT Points": 5100000,
      "image": "https://www.thesportsdb.com/images/media/player/cutout/17w6so1713902597.png",
      "Tier": "Tier 1",
      "Achievements": {
        "5x NBA Champion": true,
        "3x Finals MVP": true,
        "2x MVP": true,
        "15x All-Star": true,
        "10x All-NBA First Team": true,
        "8x All-Defensive First Team": true,
        "Rookie of the Year": true
      },
      "rank": 10
    },
    {
      "Player Name": "Stephen Curry",
      "Total GOAT Points": 4912000,
      "image": "https://www.thesportsdb.com/images/media/player/cutout/ljgyln1711802711.png",
      "Tier": "Tier 1",
      "Achievements": {
        "4x NBA Champion": true,
        "1x Finals MVP": true,
        "2x MVP": true,
        "9x All-Star": true,
        "4x All-NBA First Team": true
      },
      "rank": 11
    },
    {
      "Player Name": "Hakeem Olajuwon",
      "Total GOAT Points": 4700000,
      "image": "https://www.thesportsdb.com/images/media/player/cutout/2g6uns1526117687.png",
      "Tier": "Tier 1",
      "Achievements": {
        "2x NBA Champion": true,
        "2x Finals MVP": true,
        "1x MVP": true,
        "12x All-Star": true,
        "6x All-NBA First Team": true,
        "5x All-Defensive First Team": true
      },
      "rank": 12
    },
    {
      "Player Name": "Oscar Robertson",
      "Total GOAT Points": 4500000,
      "image": "https://www.thesportsdb.com/images/media/player/cutout/f433x31667039361.png",
      "Tier": "Tier 1",
      "Achievements": {
        "1x NBA Champion": true,
        "1x MVP": true,
        "12x All-Star": true,
        "9x All-NBA First Team": true
      },
      "rank": 13
    },
    {
      "Player Name": "Kevin Durant",
      "Total GOAT Points": 4375000,
      "image": "https://www.thesportsdb.com/images/media/player/cutout/fiem831698837888.png",
      "Tier": "Tier 1",
      "Achievements": {
        "2x NBA Champion": true,
        "2x Finals MVP": true,
        "1x MVP": true,
        "13x All-Star": true,
        "6x All-NBA First Team": true
      },
      "rank": 14
    },
    {
      "Player Name": "Kevin Garnett",
      "Total GOAT Points": 4100000,
      "image": "https://www.thesportsdb.com/images/media/player/cutout/qqtspy1424628750.png",
      "Tier": "Tier 1",
      "Achievements": {
        "1x NBA Champion": true,
        "1x MVP": true,
        "15x All-Star": true,
        "4x All-NBA First Team": true,
        "9x All-Defensive First Team": true
      },
      "rank": 15
    },
    {
      "Player Name": "Jerry West",
      "Total GOAT Points": 3900000,
      "image": "https://cdn.nba.com/headshots/nba/latest/1040x760/78497.png",
      "Tier": "Tier 1",
      "Achievements": {
        "1x NBA Champion": true,
        "1x Finals MVP": true,
        "14x All-Star": true,
        "10x All-NBA First Team": true,
        "4x All-Defensive First Team": true
      },
      "rank": 16
    },
    {
      "Player Name": "Karl Malone",
      "Total GOAT Points": 3700000,
      "image": "https://www.thesportsdb.com/images/media/player/cutout/15firm1485542853.png",
      "Tier": "Tier 1",
      "Achievements": {
        "2x MVP": true,
        "14x All-Star": true,
        "11x All-NBA First Team": true,
        "4x All-Defensive First Team": true
      },
      "rank": 17
    },
    {
      "Player Name": "Julius Erving",
      "Total GOAT Points": 3500000,
      "image": "https://www.thesportsdb.com/images/media/player/cutout/l3pw3q1586518906.png",
      "Tier": "Tier 1",
      "Achievements": {
        "1x NBA Champion": true,
        "1x MVP": true,
        "11x All-Star": true,
        "7x All-NBA First Team": true
      },
      "rank": 18
    },
    {
      "Player Name": "Dirk Nowitzki",
      "Total GOAT Points": 3300000,
      "image": "https://www.thesportsdb.com/images/media/player/cutout/jbozd11667160135.png",
      "Tier": "Tier 1",
      "Achievements": {
        "1x NBA Champion": true,
        "1x Finals MVP": true,
        "1x MVP": true,
        "14x All-Star": true,
        "4x All-NBA First Team": true,
        "5x All-NBA Second Team": true,
        "3x All-NBA Third Team": true
      },
      "rank": 19
    },
    {
      "Player Name": "Moses Malone",
      "Total GOAT Points": 3100000,
      "image": "https://www.thesportsdb.com/images/media/player/cutout/qpvjee1586520264.png",
      "Tier": "Tier 1",
      "Achievements": {
        "1x NBA Champion": true,
        "1x Finals MVP": true,
        "3x MVP": true,
        "12x All-Star": true,
        "4x All-NBA First Team": true,
        "4x All-NBA Second Team": true,
        "1x All-Defensive First Team": true,
        "1x All-Defensive Second Team": true
      },
      "rank": 20
    },
    {
      "Player Name": "Dwyane Wade",
      "Total GOAT Points": 2900000,
      "image": "https://www.thesportsdb.com/images/media/player/cutout/p8xsvg1713703379.png",
      "Tier": "Tier 1",
      "Achievements": {
        "3x NBA Champion": true,
        "1x Finals MVP": true,
        "13x All-Star": true,
        "2x All-NBA First Team": true,
        "3x All-NBA Second Team": true,
        "3x All-NBA Third Team": true,
        "3x All-Defensive Second Team": true
      },
      "rank": 21
    },
    {
      "Player Name": "Giannis Antetokounmpo",
      "Total GOAT Points": 2700000,
      "image": "https://www.thesportsdb.com/images/media/player/cutout/mschrn1702559698.png",
      "Tier": "Tier 1",
      "Achievements": {
        "1x NBA Champion": true,
        "1x Finals MVP": true,
        "2x MVP": true,
        "7x All-Star": true,
        "5x All-NBA First Team": true,
        "2x All-NBA Second Team": true,
        "1x Defensive Player of the Year": true,
        "4x All-Defensive First Team": true,
        "1x All-Defensive Second Team": true
      },
      "rank": 22
    },
    {
      "Player Name": "Nikola Jokic",
      "Total GOAT Points": 2500340,
      "image": "https://www.thesportsdb.com/images/media/player/cutout/a73zar1711897604.png",
      "Tier": "Tier 1",
      "Achievements": {
        "1x NBA Champion": true,
        "1x Finals MVP": true,
        "2x MVP": true,
        "5x All-Star": true,
        "3x All-NBA First Team": true,
        "2x All-NBA Second Team": true
      },
      "rank": 23
    },
    {
      "Player Name": "Scottie Pippen",
      "Total GOAT Points": 2300000,
      "image": "https://www.thesportsdb.com/images/media/player/cutout/63bcy61602278478.png",
      "Tier": "Tier 1",
      "Achievements": {
        "6x NBA Champion": true,
        "7x All-Star": true,
        "3x All-NBA First Team": true,
        "2x All-NBA Second Team": true,
        "2x All-NBA Third Team": true,
        "8x All-Defensive First Team": true,
        "2x All-Defensive Second Team": true
      },
      "rank": 24
    },
    {
      "Player Name": "Isiah Thomas",
      "Total GOAT Points": 2100000,
      "image": "https://cdn.nba.com/headshots/nba/latest/1040x760/78318.png",
      "Tier": "Tier 1",
      "Achievements": {
        "2x NBA Champion": true,
        "1x Finals MVP": true,
        "12x All-Star": true,
        "3x All-NBA First Team": true,
        "2x All-NBA Second Team": true
      },
      "rank": 25
    },
    {
      "Player Name": "Kawhi Leonard",
      "Total GOAT Points": 1912540,
      "image": "https://www.thesportsdb.com/images/media/player/cutout/qbgufr1609008475.png",
      "Tier": "Tier 1",
      "Achievements": {
        "2x NBA Champion": true,
        "2x Finals MVP": true,
        "2x Defensive Player of the Year": true,
        "5x All-Star": true,
        "3x All-NBA First Team": true,
        "2x All-NBA Second Team": true,
        "2x All-Defensive First Team": true,
        "5x All-Defensive Second Team": true
      },
      "rank": 26
    },
    {
      "Player Name": "Patrick Ewing",
      "Total GOAT Points": 1700000,
      "image": "https://www.thesportsdb.com/images/media/player/cutout/2zecpi1526118084.png",
      "Tier": "Tier 1",
      "Achievements": {
        "11x All-Star": true,
        "1x All-NBA First Team": true,
        "6x All-NBA Second Team": true,
        "3x All-Defensive Second Team": true,
        "Rookie of the Year": true
      },
      "rank": 27
    },
    {
      "Player Name": "Chris Paul",
      "Total GOAT Points": 1537500,
      "image": "https://www.thesportsdb.com/images/media/player/cutout/j6kup21698832453.png",
      "Tier": "Tier 1",
      "Achievements": {
        "12x All-Star": true,
        "4x All-NBA First Team": true,
        "5x All-NBA Second Team": true,
        "1x All-NBA Third Team": true,
        "7x All-Defensive First Team": true,
        "2x All-Defensive Second Team": true,
        "Rookie of the Year": true
      },
      "rank": 28
    },
    {
      "Player Name": "Allen Iverson",
      "Total GOAT Points": 1300000,
      "image": "https://www.thesportsdb.com/images/media/player/cutout/xkd6jc1602351653.png",
      "Tier": "Tier 1",
      "Achievements": {
        "1x MVP": true,
        "11x All-Star": true,
        "3x All-NBA First Team": true,
        "3x All-NBA Second Team": true,
        "1x All-NBA Third Team": true,
        "Rookie of the Year": true
      },
      "rank": 29
    },
    {
      "Player Name": "John Stockton",
      "Total GOAT Points": 1100000,
      "image": "https://www.thesportsdb.com/images/media/player/cutout/ub9e211598562588.png",
      "Tier": "Tier 1",
      "Achievements": {
        "10x All-Star": true,
        "2x All-NBA First Team": true,
        "6x All-NBA Second Team": true,
        "3x All-NBA Third Team": true,
        "5x All-Defensive Second Team": true
      },
      "rank": 30
    },
    {
      "Player Name": "David Robinson",
      "Total GOAT Points": 900000,
      "image": "https://cdn.nba.com/headshots/nba/latest/1040x760/764.png",
      "Tier": "Tier 1",
      "Achievements": {
        "2x NBA Champion": true,
        "1x MVP": true,
        "10x All-Star": true,
        "4x All-NBA First Team": true,
        "2x All-NBA Second Team": true,
        "4x All-NBA Third Team": true,
        "4x All-Defensive First Team": true,
        "4x All-Defensive Second Team": true,
        "Rookie of the Year": true
      },
      "rank": 31
    },
    {
      "Player Name": "Jayson Tatum",
      "Total GOAT Points": 800230,
      "image": "https://www.thesportsdb.com/images/media/player/cutout/ym6tpl1711802441.png",
      "Tier": "Tier 1",
      "Achievements": {
        "1x NBA Champion": true,
        "4x All-Star": true,
        "3x All-NBA First Team": true,
        "1x All-NBA Second Team": true
      },
      "rank": 32
    },
    {
      "Player Name": "Luka Doncic",
      "Total GOAT Points": 500040,
      "image": "https://www.thesportsdb.com/images/media/player/cutout/27l68o1645309356.png",
      "Tier": "Tier 1",
      "Achievements": {
        "5x All-NBA First Team": true,
        "5x All-Star": true,
        "Scoring Champion": true
      },
      "rank": 33
    },
    {
      "Player Name": "Joel Embiid",
      "Total GOAT Points": 500030,
      "image": "https://www.thesportsdb.com/images/media/player/cutout/uzvosh1645222714.png",
      "Tier": "Tier 1",
      "Achievements": {
        "1x MVP": true,
        "2x Scoring Champion": true,
        "6x All-Star": true,
        "4x All-NBA First Team": true,
        "3x All-Defensive Second Team": true
      },
      "rank": 34
    },
    {
      "Player Name": "Anthony Edwards",
      "Total GOAT Points": 500000,
      "image": "https://www.thesportsdb.com/images/media/player/cutout/d1xthv1704196318.png",
      "Tier": "Tier 1",
      "Achievements": {
        "1x All-Star": true,
        "All-Rookie First Team": true
      },
      "rank": 35
    },
    {
      "Player Name": "Jalen Brunson",
      "Total GOAT Points": 406000,
      "image": "https://www.thesportsdb.com/images/media/player/cutout/mr4fe21711892054.png",
      "Tier": "Tier 1",
      "Achievements": {
        "Most Improved Player": true,
        "1x All-NBA Second Team": true
      },
      "rank": 36
    },
    {
      "Player Name": "Victor Wembanyama",
      "Total GOAT Points": 405140,
      "image": "https://www.thesportsdb.com/images/media/player/cutout/jlrgxf1697880842.png",
      "Tier": "Got Next Tier",
      "Achievements": {
        "Rookie of the Year": true,
        "1x All-Defensive First Team": true
      },
      "rank": 37
    },
    {
      "Player Name": "Zion Williamson",
      "Total GOAT Points": 50000,
      "image": "https://www.thesportsdb.com/images/media/player/cutout/zplz8c1709062721.png",
      "Tier": "Tier 1",
      "Achievements": {
        "1x All-Star": true,
        "All-Rookie First Team": true
      },
      "rank": 38
    },
    {
      "Player Name": "Lance Toledo",
      "Total GOAT Points": 0,
      "image": "https://i.imgur.com/StRMTRG.png",
      "Tier": "Got Next Tier",
      "Achievements": {
        "win_championship_as_rookie": false,
        "rookie_finals_mvp": false,
        "rookie_of_the_year": false,
        "most_rookie_triple_doubles": false,
        "most_rookie_blocks": false,
        "most_rookie_rebounds": false,
        "most_rookie_points": false,
        "most_rookie_steals": false,
        "most_rookie_assists": false,
        "most_rookie_3pm": false,
        "2nd_most_rookie_triple_doubles": false,
        "2nd_most_rookie_blocks": false,
        "2nd_most_rookie_assists": false,
        "2nd_most_rookie_steals": false,
        "2nd_most_rookie_3pm": false,
        "2nd_most_rookie_points": false,
        "2nd_most_rookie_rebounds": false,
        "3rd_most_rookie_triple_doubles": false,
        "3rd_most_rookie_3pm": false,
        "3rd_most_rookie_steals": false,
        "3rd_most_rookie_points": false,
        "3rd_most_rookie_rebounds": false,
        "3rd_most_rookie_assists": false,
        "3rd_most_rookie_blocks": false,
        "4th_most_rookie_blocks": false,
        "4th_most_rookie_rebounds": false,
        "4th_most_rookie_triple_doubles": false,
        "4th_most_rookie_steals": false,
        "4th_most_rookie_assists": false,
        "4th_most_rookie_3pm": false,
        "4th_most_rookie_points": false,
        "5th_most_rookie_rebounds": false,
        "5th_most_rookie_assists": false,
        "5th_most_rookie_triple_doubles": false,
        "5th_most_rookie_3pm": false,
        "5th_most_rookie_steals": false,
        "5th_most_rookie_blocks": false,
        "5th_most_rookie_points": false,
        "rookie_all_star": false,
        "time_all_star": 0,
        "10x_all_star": false,
        "12_championships": false,
        "7_championships": false,
        "6_championships": false,
        "5_championships": false,
        "3_peat_championships": false,
        "2nd_3_peat": false,
        "6_0_in_finals": false,
        "back_to_back_championships": false,
        "championship_with_no_90__ovr": 0,
        "championship_with_1_player_90__ovr": 0,
        "championship_with_2_players_90__ovr": 0,
        "championship_with_3__players_90__ovr": 0,
        "championship_as_7th_8th_seed": 0,
        "win_an_mvp": 0,
        "back_to_back_mvps": false,
        "5_mvps": false,
        "4_mvps": false,
        "3_peat_mvps": false,
        "4_consecutive_mvps": false,
        "5_consecutive_mvps": false,
        "time_dpoy": 0,
        "back_to_back_dpoys": false,
        "5_dpoys": false,
        "4_dpoys": false,
        "3_peat_dpoys": false,
        "4_consecutive_dpoys": false,
        "5_consecutive_dpoys": false,
        "time_1st_team_all_nba": 0,
        "time_2nd_team_all_nba": 0,
        "time_3rd_team_all_nba": 0,
        "1st_team_all_defensive": 0,
        "2nd_team_all_defensive": 0,
        "record_100_points_in_game": false,
        "record_55_rebounds_in_game": false,
        "record_30_assists_in_game": false,
        "record_17_blocks_in_game": false,
        "record_14_3pm_in_game": false,
        "record_11_steals_in_game": false,
        "2nd_most_points_in_game": false,
        "2nd_most_rebounds_in_game": false,
        "2nd_most_assists_in_game": false,
        "2nd_most_blocks_in_game": false,
        "2nd_most_3pm_in_game": false,
        "2nd_most_steals_in_game": false,
        "3rd_most_points_in_game": false,
        "3rd_most_rebounds_in_game": false,
        "3rd_most_assists_in_game": false,
        "3rd_most_blocks_in_game": false,
        "3rd_most_3pm_in_game": false,
        "3rd_most_steals_in_game": false,
        "record_playoff_points": false,
        "record_playoff_rebounds": false,
        "record_playoff_assists": false,
        "record_playoff_blocks": false,
        "record_playoff_steals": false,
        "record_playoff_3pm": false,
        "career_points_record": false,
        "career_assists_record": false,
        "career_rebounds_record": false,
        "career_blocks_record": false,
        "career_steals_record": false,
        "career_3pm_record": false,
        "career_triple_doubles_record": false,
        "career_40_point_games_record": false,
        "career_50_point_games_record": false,
        "2nd_most_career_points": false,
        "2nd_most_career_assists": false,
        "2nd_most_career_rebounds": false,
        "2nd_most_career_blocks": false,
        "2nd_most_career_steals": false,
        "2nd_most_career_3pm": false,
        "2nd_most_career_triple_doubles": false,
        "2nd_most_career_40_point_games": false,
        "2nd_most_career_50_point_games": false,
        "quadruple_double": false,
        "quintuple_double": false,
        "triple_double": false,
        "60_points_and_triple_double": false,
        "60_20_10_triple_double": false,
        "20_20_20_triple_double": false,
        "40__points_in_game": false,
        "50__points_in_game": false,
        "60__points_in_game": false,
        "71__points_in_game": false,
        "30__points_with_90__fg_": false,
        "27__rebounds_in_game": false,
        "15__rebounds_in_game": false,
        "12__rebounds_in_game": false,
        "6__blocks_in_game": false,
        "5__blocks_in_game": false,
        "4__blocks_in_game": false,
        "5__steals_in_game": false,
        "3__steals_in_game": false,
        "15__assists_in_game": false,
        "14__assists_in_game": false,
        "10__assists_in_game": false,
        "6__3pm_in_game": false,
        "5__3pm_in_game": false,
        "4__3pm_in_game": false,
        "10_fgm_without_miss": false,
        "fastest_to_30_000_points": false,
        "fastest_to_20_000_points": false,
        "fastest_to_10_000_points": false,
        "fastest_to_5_000_points": false,
        "fastest_to_3_000_blocks": false,
        "fastest_to_2_000_points": false,
        "fastest_to_1_000_blocks": false,
        "avg_20_10_5_for_5__seasons": false,
        "5_000_points___1_500_assists_in_200_games": false,
        "new_playoff_high_assists": false,
        "new_playoff_high_blocks": false,
        "new_playoff_high_steals": false,
        "new_playoff_high_points": false,
        "new_playoff_high_3pm": false,
        "new_playoff_high_rebounds": false,
        "undefeated_playoff_run": false,
        "reverse_sweep_in_playoffs": false,
        "reverse_sweep_top_seed": false,
        "20_game_win_streak": false,
        "10_game_win_streak": false,
        "5_game_win_streak": false,
        "player_of_the_month": false,
        "sweep_top_seed_in_playoffs": false,
        "sweep_playoff_series": false,
        "sweep_season_series": false,
        "beat_previous_season_s_champions": false,
        "better_rookie_debut_than_lebron": false,
        "better_rookie_debut_than_mj": false,
        "eliminate_former_team_in_playoffs": false,
        "eliminate_top_seed_in_playoffs": false,
        "eliminate_rival_team_in_playoffs": false,
        "win_finals_rematch": false,
        "clinching_playoffs": false,
        "clinch_playoffs_in_finale": false,
        "league_leader_in_multiple_stats": false,
        "first_triple_double": false,
        "triple_double_in_playoffs": false,
        "quadruple_double_in_playoffs": false,
        "double_double_with_no_turnovers_in_playoffs": false,
        "100__fg_in_playoffs__min_10_shots_": false,
        "759__points_in_single_playoff_run": false,
        "top_kobe_s_81_points": false,
        "all_star_game_mvp": false,
        "finals_mvp": false,
        "50_40_90_season": false,
        "lead_league_in_scoring": false,
        "lead_league_in_rebounds": false,
        "lead_league_in_assists": false,
        "lead_league_in_blocks": false,
        "lead_league_in_steals": false,
        "lead_league_in_3pm": false,
        "all_defensive_first_team": false,
        "all_defensive_second_team": false,
        "scoring_title": false,
        "rebounding_title": false,
        "assist_title": false,
        "blocks_title": false,
        "steals_title": false,
        "3pm_title": false
      },
      "rank": 39
    },
    {
      "Player Name": "Frankie Maravilla",
      "Total GOAT Points": 0,
      "image": "https://i.imgur.com/GjW8sxH.png",
      "Tier": "Got Next Tier",
      "Achievements": {
        "win_championship_as_rookie": false,
        "rookie_finals_mvp": false,
        "rookie_of_the_year": false,
        "most_rookie_triple_doubles": false,
        "most_rookie_blocks": false,
        "most_rookie_rebounds": false,
        "most_rookie_points": false,
        "most_rookie_steals": false,
        "most_rookie_assists": false,
        "most_rookie_3pm": false,
        "2nd_most_rookie_triple_doubles": false,
        "2nd_most_rookie_blocks": false,
        "2nd_most_rookie_assists": false,
        "2nd_most_rookie_steals": false,
        "2nd_most_rookie_3pm": false,
        "2nd_most_rookie_points": false,
        "2nd_most_rookie_rebounds": false,
        "3rd_most_rookie_triple_doubles": false,
        "3rd_most_rookie_3pm": false,
        "3rd_most_rookie_steals": false,
        "3rd_most_rookie_points": false,
        "3rd_most_rookie_rebounds": false,
        "3rd_most_rookie_assists": false,
        "3rd_most_rookie_blocks": false,
        "4th_most_rookie_blocks": false,
        "4th_most_rookie_rebounds": false,
        "4th_most_rookie_triple_doubles": false,
        "4th_most_rookie_steals": false,
        "4th_most_rookie_assists": false,
        "4th_most_rookie_3pm": false,
        "4th_most_rookie_points": false,
        "5th_most_rookie_rebounds": false,
        "5th_most_rookie_assists": false,
        "5th_most_rookie_triple_doubles": false,
        "5th_most_rookie_3pm": false,
        "5th_most_rookie_steals": false,
        "5th_most_rookie_blocks": false,
        "5th_most_rookie_points": false,
        "rookie_all_star": false,
        "time_all_star": 0,
        "10x_all_star": false,
        "12_championships": false,
        "7_championships": false,
        "6_championships": false,
        "5_championships": false,
        "3_peat_championships": false,
        "2nd_3_peat": false,
        "6_0_in_finals": false,
        "back_to_back_championships": false,
        "championship_with_no_90__ovr": 0,
        "championship_with_1_player_90__ovr": 0,
        "championship_with_2_players_90__ovr": 0,
        "championship_with_3__players_90__ovr": 0,
        "championship_as_7th_8th_seed": 0,
        "win_an_mvp": 0,
        "back_to_back_mvps": false,
        "5_mvps": false,
        "4_mvps": false,
        "3_peat_mvps": false,
        "4_consecutive_mvps": false,
        "5_consecutive_mvps": false,
        "time_dpoy": 0,
        "back_to_back_dpoys": false,
        "5_dpoys": false,
        "4_dpoys": false,
        "3_peat_dpoys": false,
        "4_consecutive_dpoys": false,
        "5_consecutive_dpoys": false,
        "time_1st_team_all_nba": 0,
        "time_2nd_team_all_nba": 0,
        "time_3rd_team_all_nba": 0,
        "1st_team_all_defensive": 0,
        "2nd_team_all_defensive": 0,
        "record_100_points_in_game": false,
        "record_55_rebounds_in_game": false,
        "record_30_assists_in_game": false,
        "record_17_blocks_in_game": false,
        "record_14_3pm_in_game": false,
        "record_11_steals_in_game": false,
        "2nd_most_points_in_game": false,
        "2nd_most_rebounds_in_game": false,
        "2nd_most_assists_in_game": false,
        "2nd_most_blocks_in_game": false,
        "2nd_most_3pm_in_game": false,
        "2nd_most_steals_in_game": false,
        "3rd_most_points_in_game": false,
        "3rd_most_rebounds_in_game": false,
        "3rd_most_assists_in_game": false,
        "3rd_most_blocks_in_game": false,
        "3rd_most_3pm_in_game": false,
        "3rd_most_steals_in_game": false,
        "record_playoff_points": false,
        "record_playoff_rebounds": false,
        "record_playoff_assists": false,
        "record_playoff_blocks": false,
        "record_playoff_steals": false,
        "record_playoff_3pm": false,
        "career_points_record": false,
        "career_assists_record": false,
        "career_rebounds_record": false,
        "career_blocks_record": false,
        "career_steals_record": false,
        "career_3pm_record": false,
        "career_triple_doubles_record": false,
        "career_40_point_games_record": false,
        "career_50_point_games_record": false,
        "2nd_most_career_points": false,
        "2nd_most_career_assists": false,
        "2nd_most_career_rebounds": false,
        "2nd_most_career_blocks": false,
        "2nd_most_career_steals": false,
        "2nd_most_career_3pm": false,
        "2nd_most_career_triple_doubles": false,
        "2nd_most_career_40_point_games": false,
        "2nd_most_career_50_point_games": false,
        "quadruple_double": false,
        "quintuple_double": false,
        "triple_double": false,
        "60_points_and_triple_double": false,
        "60_20_10_triple_double": false,
        "20_20_20_triple_double": false,
        "40__points_in_game": false,
        "50__points_in_game": false,
        "60__points_in_game": false,
        "71__points_in_game": false,
        "30__points_with_90__fg_": false,
        "27__rebounds_in_game": false,
        "15__rebounds_in_game": false,
        "12__rebounds_in_game": false,
        "6__blocks_in_game": false,
        "5__blocks_in_game": false,
        "4__blocks_in_game": false,
        "5__steals_in_game": false,
        "3__steals_in_game": false,
        "15__assists_in_game": false,
        "14__assists_in_game": false,
        "10__assists_in_game": false,
        "6__3pm_in_game": false,
        "5__3pm_in_game": false,
        "4__3pm_in_game": false,
        "10_fgm_without_miss": false,
        "fastest_to_30_000_points": false,
        "fastest_to_20_000_points": false,
        "fastest_to_10_000_points": false,
        "fastest_to_5_000_points": false,
        "fastest_to_3_000_blocks": false,
        "fastest_to_2_000_points": false,
        "fastest_to_1_000_blocks": false,
        "avg_20_10_5_for_5__seasons": false,
        "5_000_points___1_500_assists_in_200_games": false,
        "new_playoff_high_assists": false,
        "new_playoff_high_blocks": false,
        "new_playoff_high_steals": false,
        "new_playoff_high_points": false,
        "new_playoff_high_3pm": false,
        "new_playoff_high_rebounds": false,
        "undefeated_playoff_run": false,
        "reverse_sweep_in_playoffs": false,
        "reverse_sweep_top_seed": false,
        "20_game_win_streak": false,
        "10_game_win_streak": false,
        "5_game_win_streak": false,
        "player_of_the_month": false,
        "sweep_top_seed_in_playoffs": false,
        "sweep_playoff_series": false,
        "sweep_season_series": false,
        "beat_previous_season_s_champions": false,
        "better_rookie_debut_than_lebron": false,
        "better_rookie_debut_than_mj": false,
        "eliminate_former_team_in_playoffs": false,
        "eliminate_top_seed_in_playoffs": false,
        "eliminate_rival_team_in_playoffs": false,
        "win_finals_rematch": false,
        "clinching_playoffs": false,
        "clinch_playoffs_in_finale": false,
        "league_leader_in_multiple_stats": false,
        "first_triple_double": false,
        "triple_double_in_playoffs": false,
        "quadruple_double_in_playoffs": false,
        "double_double_with_no_turnovers_in_playoffs": false,
        "100__fg_in_playoffs__min_10_shots_": false,
        "759__points_in_single_playoff_run": false,
        "top_kobe_s_81_points": false,
        "all_star_game_mvp": false,
        "finals_mvp": false,
        "50_40_90_season": false,
        "lead_league_in_scoring": false,
        "lead_league_in_rebounds": false,
        "lead_league_in_assists": false,
        "lead_league_in_blocks": false,
        "lead_league_in_steals": false,
        "lead_league_in_3pm": false,
        "all_defensive_first_team": false,
        "all_defensive_second_team": false,
        "scoring_title": false,
        "rebounding_title": false,
        "assist_title": false,
        "blocks_title": false,
        "steals_title": false,
        "3pm_title": false
      },
      "rank": 40
    },
    {
      "Player Name": "Dequan Foster",
      "Total GOAT Points": 0,
      "image": "https://i.imgur.com/pC3SM3X.png",
      "Tier": "Got Next Tier",
      "Achievements": {
        "win_championship_as_rookie": false,
        "rookie_finals_mvp": false,
        "rookie_of_the_year": false,
        "most_rookie_triple_doubles": false,
        "most_rookie_blocks": false,
        "most_rookie_rebounds": false,
        "most_rookie_points": false,
        "most_rookie_steals": false,
        "most_rookie_assists": false,
        "most_rookie_3pm": false,
        "2nd_most_rookie_triple_doubles": false,
        "2nd_most_rookie_blocks": false,
        "2nd_most_rookie_assists": false,
        "2nd_most_rookie_steals": false,
        "2nd_most_rookie_3pm": false,
        "2nd_most_rookie_points": false,
        "2nd_most_rookie_rebounds": false,
        "3rd_most_rookie_triple_doubles": false,
        "3rd_most_rookie_3pm": false,
        "3rd_most_rookie_steals": false,
        "3rd_most_rookie_points": false,
        "3rd_most_rookie_rebounds": false,
        "3rd_most_rookie_assists": false,
        "3rd_most_rookie_blocks": false,
        "4th_most_rookie_blocks": false,
        "4th_most_rookie_rebounds": false,
        "4th_most_rookie_triple_doubles": false,
        "4th_most_rookie_steals": false,
        "4th_most_rookie_assists": false,
        "4th_most_rookie_3pm": false,
        "4th_most_rookie_points": false,
        "5th_most_rookie_rebounds": false,
        "5th_most_rookie_assists": false,
        "5th_most_rookie_triple_doubles": false,
        "5th_most_rookie_3pm": false,
        "5th_most_rookie_steals": false,
        "5th_most_rookie_blocks": false,
        "5th_most_rookie_points": false,
        "rookie_all_star": false,
        "time_all_star": 0,
        "10x_all_star": false,
        "12_championships": false,
        "7_championships": false,
        "6_championships": false,
        "5_championships": false,
        "3_peat_championships": false,
        "2nd_3_peat": false,
        "6_0_in_finals": false,
        "back_to_back_championships": false,
        "championship_with_no_90__ovr": 0,
        "championship_with_1_player_90__ovr": 0,
        "championship_with_2_players_90__ovr": 0,
        "championship_with_3__players_90__ovr": 0,
        "championship_as_7th_8th_seed": 0,
        "win_an_mvp": 0,
        "back_to_back_mvps": false,
        "5_mvps": false,
        "4_mvps": false,
        "3_peat_mvps": false,
        "4_consecutive_mvps": false,
        "5_consecutive_mvps": false,
        "time_dpoy": 0,
        "back_to_back_dpoys": false,
        "5_dpoys": false,
        "4_dpoys": false,
        "3_peat_dpoys": false,
        "4_consecutive_dpoys": false,
        "5_consecutive_dpoys": false,
        "time_1st_team_all_nba": 0,
        "time_2nd_team_all_nba": 0,
        "time_3rd_team_all_nba": 0,
        "1st_team_all_defensive": 0,
        "2nd_team_all_defensive": 0,
        "record_100_points_in_game": false,
        "record_55_rebounds_in_game": false,
        "record_30_assists_in_game": false,
        "record_17_blocks_in_game": false,
        "record_14_3pm_in_game": false,
        "record_11_steals_in_game": false,
        "2nd_most_points_in_game": false,
        "2nd_most_rebounds_in_game": false,
        "2nd_most_assists_in_game": false,
        "2nd_most_blocks_in_game": false,
        "2nd_most_3pm_in_game": false,
        "2nd_most_steals_in_game": false,
        "3rd_most_points_in_game": false,
        "3rd_most_rebounds_in_game": false,
        "3rd_most_assists_in_game": false,
        "3rd_most_blocks_in_game": false,
        "3rd_most_3pm_in_game": false,
        "3rd_most_steals_in_game": false,
        "record_playoff_points": false,
        "record_playoff_rebounds": false,
        "record_playoff_assists": false,
        "record_playoff_blocks": false,
        "record_playoff_steals": false,
        "record_playoff_3pm": false,
        "career_points_record": false,
        "career_assists_record": false,
        "career_rebounds_record": false,
        "career_blocks_record": false,
        "career_steals_record": false,
        "career_3pm_record": false,
        "career_triple_doubles_record": false,
        "career_40_point_games_record": false,
        "career_50_point_games_record": false,
        "2nd_most_career_points": false,
        "2nd_most_career_assists": false,
        "2nd_most_career_rebounds": false,
        "2nd_most_career_blocks": false,
        "2nd_most_career_steals": false,
        "2nd_most_career_3pm": false,
        "2nd_most_career_triple_doubles": false,
        "2nd_most_career_40_point_games": false,
        "2nd_most_career_50_point_games": false,
        "quadruple_double": false,
        "quintuple_double": false,
        "triple_double": false,
        "60_points_and_triple_double": false,
        "60_20_10_triple_double": false,
        "20_20_20_triple_double": false,
        "40__points_in_game": false,
        "50__points_in_game": false,
        "60__points_in_game": false,
        "71__points_in_game": false,
        "30__points_with_90__fg_": false,
        "27__rebounds_in_game": false,
        "15__rebounds_in_game": false,
        "12__rebounds_in_game": false,
        "6__blocks_in_game": false,
        "5__blocks_in_game": false,
        "4__blocks_in_game": false,
        "5__steals_in_game": false,
        "3__steals_in_game": false,
        "15__assists_in_game": false,
        "14__assists_in_game": false,
        "10__assists_in_game": false,
        "6__3pm_in_game": false,
        "5__3pm_in_game": false,
        "4__3pm_in_game": false,
        "10_fgm_without_miss": false,
        "fastest_to_30_000_points": false,
        "fastest_to_20_000_points": false,
        "fastest_to_10_000_points": false,
        "fastest_to_5_000_points": false,
        "fastest_to_3_000_blocks": false,
        "fastest_to_2_000_points": false,
        "fastest_to_1_000_blocks": false,
        "avg_20_10_5_for_5__seasons": false,
        "5_000_points___1_500_assists_in_200_games": false,
        "new_playoff_high_assists": false,
        "new_playoff_high_blocks": false,
        "new_playoff_high_steals": false,
        "new_playoff_high_points": false,
        "new_playoff_high_3pm": false,
        "new_playoff_high_rebounds": false,
        "undefeated_playoff_run": false,
        "reverse_sweep_in_playoffs": false,
        "reverse_sweep_top_seed": false,
        "20_game_win_streak": false,
        "10_game_win_streak": false,
        "5_game_win_streak": false,
        "player_of_the_month": false,
        "sweep_top_seed_in_playoffs": false,
        "sweep_playoff_series": false,
        "sweep_season_series": false,
        "beat_previous_season_s_champions": false,
        "better_rookie_debut_than_lebron": false,
        "better_rookie_debut_than_mj": false,
        "eliminate_former_team_in_playoffs": false,
        "eliminate_top_seed_in_playoffs": false,
        "eliminate_rival_team_in_playoffs": false,
        "win_finals_rematch": false,
        "clinching_playoffs": false,
        "clinch_playoffs_in_finale": false,
        "league_leader_in_multiple_stats": false,
        "first_triple_double": false,
        "triple_double_in_playoffs": false,
        "quadruple_double_in_playoffs": false,
        "double_double_with_no_turnovers_in_playoffs": false,
        "100__fg_in_playoffs__min_10_shots_": false,
        "759__points_in_single_playoff_run": false,
        "top_kobe_s_81_points": false,
        "all_star_game_mvp": false,
        "finals_mvp": false,
        "50_40_90_season": false,
        "lead_league_in_scoring": false,
        "lead_league_in_rebounds": false,
        "lead_league_in_assists": false,
        "lead_league_in_blocks": false,
        "lead_league_in_steals": false,
        "lead_league_in_3pm": false,
        "all_defensive_first_team": false,
        "all_defensive_second_team": false,
        "scoring_title": false,
        "rebounding_title": false,
        "assist_title": false,
        "blocks_title": false,
        "steals_title": false,
        "3pm_title": false
      },
      "rank": 41
    },
    {
      "Player Name": "Kris Ynoa",
      "Total GOAT Points": 0,
      "image": "https://i.imgur.com/SYKJtRI.png",
      "Tier": "Got Next Tier",
      "Achievements": {
        "win_championship_as_rookie": false,
        "rookie_finals_mvp": false,
        "rookie_of_the_year": false,
        "most_rookie_triple_doubles": false,
        "most_rookie_blocks": false,
        "most_rookie_rebounds": false,
        "most_rookie_points": false,
        "most_rookie_steals": false,
        "most_rookie_assists": false,
        "most_rookie_3pm": false,
        "2nd_most_rookie_triple_doubles": false,
        "2nd_most_rookie_blocks": false,
        "2nd_most_rookie_assists": false,
        "2nd_most_rookie_steals": false,
        "2nd_most_rookie_3pm": false,
        "2nd_most_rookie_points": false,
        "2nd_most_rookie_rebounds": false,
        "3rd_most_rookie_triple_doubles": false,
        "3rd_most_rookie_3pm": false,
        "3rd_most_rookie_steals": false,
        "3rd_most_rookie_points": false,
        "3rd_most_rookie_rebounds": false,
        "3rd_most_rookie_assists": false,
        "3rd_most_rookie_blocks": false,
        "4th_most_rookie_blocks": false,
        "4th_most_rookie_rebounds": false,
        "4th_most_rookie_triple_doubles": false,
        "4th_most_rookie_steals": false,
        "4th_most_rookie_assists": false,
        "4th_most_rookie_3pm": false,
        "4th_most_rookie_points": false,
        "5th_most_rookie_rebounds": false,
        "5th_most_rookie_assists": false,
        "5th_most_rookie_triple_doubles": false,
        "5th_most_rookie_3pm": false,
        "5th_most_rookie_steals": false,
        "5th_most_rookie_blocks": false,
        "5th_most_rookie_points": false,
        "rookie_all_star": false,
        "time_all_star": 0,
        "10x_all_star": false,
        "12_championships": false,
        "7_championships": false,
        "6_championships": false,
        "5_championships": false,
        "3_peat_championships": false,
        "2nd_3_peat": false,
        "6_0_in_finals": false,
        "back_to_back_championships": false,
        "championship_with_no_90__ovr": 0,
        "championship_with_1_player_90__ovr": 0,
        "championship_with_2_players_90__ovr": 0,
        "championship_with_3__players_90__ovr": 0,
        "championship_as_7th_8th_seed": 0,
        "win_an_mvp": 0,
        "back_to_back_mvps": false,
        "5_mvps": false,
        "4_mvps": false,
        "3_peat_mvps": false,
        "4_consecutive_mvps": false,
        "5_consecutive_mvps": false,
        "time_dpoy": 0,
        "back_to_back_dpoys": false,
        "5_dpoys": false,
        "4_dpoys": false,
        "3_peat_dpoys": false,
        "4_consecutive_dpoys": false,
        "5_consecutive_dpoys": false,
        "time_1st_team_all_nba": 0,
        "time_2nd_team_all_nba": 0,
        "time_3rd_team_all_nba": 0,
        "1st_team_all_defensive": 0,
        "2nd_team_all_defensive": 0,
        "record_100_points_in_game": false,
        "record_55_rebounds_in_game": false,
        "record_30_assists_in_game": false,
        "record_17_blocks_in_game": false,
        "record_14_3pm_in_game": false,
        "record_11_steals_in_game": false,
        "2nd_most_points_in_game": false,
        "2nd_most_rebounds_in_game": false,
        "2nd_most_assists_in_game": false,
        "2nd_most_blocks_in_game": false,
        "2nd_most_3pm_in_game": false,
        "2nd_most_steals_in_game": false,
        "3rd_most_points_in_game": false,
        "3rd_most_rebounds_in_game": false,
        "3rd_most_assists_in_game": false,
        "3rd_most_blocks_in_game": false,
        "3rd_most_3pm_in_game": false,
        "3rd_most_steals_in_game": false,
        "record_playoff_points": false,
        "record_playoff_rebounds": false,
        "record_playoff_assists": false,
        "record_playoff_blocks": false,
        "record_playoff_steals": false,
        "record_playoff_3pm": false,
        "career_points_record": false,
        "career_assists_record": false,
        "career_rebounds_record": false,
        "career_blocks_record": false,
        "career_steals_record": false,
        "career_3pm_record": false,
        "career_triple_doubles_record": false,
        "career_40_point_games_record": false,
        "career_50_point_games_record": false,
        "2nd_most_career_points": false,
        "2nd_most_career_assists": false,
        "2nd_most_career_rebounds": false,
        "2nd_most_career_blocks": false,
        "2nd_most_career_steals": false,
        "2nd_most_career_3pm": false,
        "2nd_most_career_triple_doubles": false,
        "2nd_most_career_40_point_games": false,
        "2nd_most_career_50_point_games": false,
        "quadruple_double": false,
        "quintuple_double": false,
        "triple_double": false,
        "60_points_and_triple_double": false,
        "60_20_10_triple_double": false,
        "20_20_20_triple_double": false,
        "40__points_in_game": false,
        "50__points_in_game": false,
        "60__points_in_game": false,
        "71__points_in_game": false,
        "30__points_with_90__fg_": false,
        "27__rebounds_in_game": false,
        "15__rebounds_in_game": false,
        "12__rebounds_in_game": false,
        "6__blocks_in_game": false,
        "5__blocks_in_game": false,
        "4__blocks_in_game": false,
        "5__steals_in_game": false,
        "3__steals_in_game": false,
        "15__assists_in_game": false,
        "14__assists_in_game": false,
        "10__assists_in_game": false,
        "6__3pm_in_game": false,
        "5__3pm_in_game": false,
        "4__3pm_in_game": false,
        "10_fgm_without_miss": false,
        "fastest_to_30_000_points": false,
        "fastest_to_20_000_points": false,
        "fastest_to_10_000_points": false,
        "fastest_to_5_000_points": false,
        "fastest_to_3_000_blocks": false,
        "fastest_to_2_000_points": false,
        "fastest_to_1_000_blocks": false,
        "avg_20_10_5_for_5__seasons": false,
        "5_000_points___1_500_assists_in_200_games": false,
        "new_playoff_high_assists": false,
        "new_playoff_high_blocks": false,
        "new_playoff_high_steals": false,
        "new_playoff_high_points": false,
        "new_playoff_high_3pm": false,
        "new_playoff_high_rebounds": false,
        "undefeated_playoff_run": false,
        "reverse_sweep_in_playoffs": false,
        "reverse_sweep_top_seed": false,
        "20_game_win_streak": false,
        "10_game_win_streak": false,
        "5_game_win_streak": false,
        "player_of_the_month": false,
        "sweep_top_seed_in_playoffs": false,
        "sweep_playoff_series": false,
        "sweep_season_series": false,
        "beat_previous_season_s_champions": false,
        "better_rookie_debut_than_lebron": false,
        "better_rookie_debut_than_mj": false,
        "eliminate_former_team_in_playoffs": false,
        "eliminate_top_seed_in_playoffs": false,
        "eliminate_rival_team_in_playoffs": false,
        "win_finals_rematch": false,
        "clinching_playoffs": false,
        "clinch_playoffs_in_finale": false,
        "league_leader_in_multiple_stats": false,
        "first_triple_double": false,
        "triple_double_in_playoffs": false,
        "quadruple_double_in_playoffs": false,
        "double_double_with_no_turnovers_in_playoffs": false,
        "100__fg_in_playoffs__min_10_shots_": false,
        "759__points_in_single_playoff_run": false,
        "top_kobe_s_81_points": false,
        "all_star_game_mvp": false,
        "finals_mvp": false,
        "50_40_90_season": false,
        "lead_league_in_scoring": false,
        "lead_league_in_rebounds": false,
        "lead_league_in_assists": false,
        "lead_league_in_blocks": false,
        "lead_league_in_steals": false,
        "lead_league_in_3pm": false,
        "all_defensive_first_team": false,
        "all_defensive_second_team": false,
        "scoring_title": false,
        "rebounding_title": false,
        "assist_title": false,
        "blocks_title": false,
        "steals_title": false,
        "3pm_title": false
      },
      "rank": 42
    },
    {}
  ]
}